README.txt
setup.py
CherrypyMako/__init__.py
CherrypyMako/mako_tool.py
CherrypyMako.egg-info/PKG-INFO
CherrypyMako.egg-info/SOURCES.txt
CherrypyMako.egg-info/dependency_links.txt
CherrypyMako.egg-info/requires.txt
CherrypyMako.egg-info/top_level.txt